{
  "timestamp": "2026-01-13 22:14:02",
  "fiyatlar": {
    "Gramaltin": {
      "Alış": "6371.66",
      "Satış": "6372.45"
    },
    "Gumus": {
      "Alış": "121.31",
      "Satış": "121.41"
    },
    "Ons": {
      "Alış": "0",
      "Satış": "0"
    },
    "Gramhasaltin": {
      "Alış": "6339.8",
      "Satış": "6340.59"
    },
    "Ceyrekaltin": {
      "Alış": "10312.81",
      "Satış": "10547.93"
    },
    "Yarimaltin": {
      "Alış": "20561.17",
      "Satış": "21095.87"
    },
    "Tamaltin": {
      "Alış": "41251.25",
      "Satış": "42062.71"
    },
    "Cumhuriyetaltini": {
      "Alış": "42719",
      "Satış": "43365"
    },
    "Ataaltin": {
      "Alış": "42540.35",
      "Satış": "43611.03"
    },
    "14Ayaraltin": {
      "Alış": "3673.94",
      "Satış": "3677.26"
    },
    "18Ayaraltin": {
      "Alış": "4705.22",
      "Satış": "4709.48"
    },
    "22Ayarbilezik": {
      "Alış": "5878.3",
      "Satış": "5883.62"
    },
    "Ikibucukaltin": {
      "Alış": "103128.13",
      "Satış": "104769.7"
    },
    "Beslialtin": {
      "Alış": "208834.46",
      "Satış": "212894.09"
    },
    "Gremsealtin": {
      "Alış": "103128.13",
      "Satış": "105479.34"
    },
    "Resataltin": {
      "Alış": "42540.35",
      "Satış": "43611.03"
    },
    "Hamitaltin": {
      "Alış": "42540.35",
      "Satış": "43611.03"
    },
    "Gramplatin": {
      "Alış": "3256.66",
      "Satış": "3262.96"
    },
    "Grampaladyum": {
      "Alış": "2575.72",
      "Satış": "2588.53"
    }
  }
}