{
  "timestamp": "2026-01-21 14:49:03",
  "fiyatlar": {
    "Gramaltin": {
      "Alış": "6762.91",
      "Satış": "6763.72"
    },
    "Gumus": {
      "Alış": "131.75",
      "Satış": "131.82"
    },
    "Ons": {
      "Alış": "0",
      "Satış": "0"
    },
    "Gramhasaltin": {
      "Alış": "6729.1",
      "Satış": "6729.9"
    },
    "Ceyrekaltin": {
      "Alış": "10982.89",
      "Satış": "11232.85"
    },
    "Yarimaltin": {
      "Alış": "21897.15",
      "Satış": "22465.71"
    },
    "Tamaltin": {
      "Alış": "43931.58",
      "Satış": "44794.01"
    },
    "Cumhuriyetaltini": {
      "Alış": "45572",
      "Satış": "46260"
    },
    "Ataaltin": {
      "Alış": "45304.44",
      "Satış": "46442.87"
    },
    "14Ayaraltin": {
      "Alış": "3912.66",
      "Satış": "3916.04"
    },
    "18Ayaraltin": {
      "Alış": "5010.95",
      "Satış": "5015.28"
    },
    "22Ayarbilezik": {
      "Alış": "6260.25",
      "Satış": "6265.67"
    },
    "Ikibucukaltin": {
      "Alış": "109828.94",
      "Satış": "111572.81"
    },
    "Beslialtin": {
      "Alış": "222403.61",
      "Satış": "226718.15"
    },
    "Gremsealtin": {
      "Alış": "109828.94",
      "Satış": "112328.54"
    },
    "Resataltin": {
      "Alış": "45304.44",
      "Satış": "46442.87"
    },
    "Hamitaltin": {
      "Alış": "45304.44",
      "Satış": "46442.87"
    },
    "Gramplatin": {
      "Alış": "3443.43",
      "Satış": "3454.1"
    },
    "Grampaladyum": {
      "Alış": "2583.15",
      "Satış": "2594.96"
    }
  }
}