{
  "timestamp": "2025-12-30 13:43:02",
  "fiyatlar": {
    "Gramaltin": {
      "Alış": "6047.44",
      "Satış": "6048.21"
    },
    "Gumus": {
      "Alış": "102.79",
      "Satış": "102.86"
    },
    "Ons": {
      "Alış": "0",
      "Satış": "0"
    },
    "Gramhasaltin": {
      "Alış": "6017.2",
      "Satış": "6017.97"
    },
    "Ceyrekaltin": {
      "Alış": "9876.34",
      "Satış": "10101.8"
    },
    "Yarimaltin": {
      "Alış": "19690.96",
      "Satış": "20203.59"
    },
    "Tamaltin": {
      "Alış": "39505.37",
      "Satış": "40283.61"
    },
    "Cumhuriyetaltini": {
      "Alış": "40757",
      "Satış": "41369"
    },
    "Ataaltin": {
      "Alış": "40739.91",
      "Satış": "41766.44"
    },
    "14Ayaraltin": {
      "Alış": "3518.45",
      "Satış": "3521.73"
    },
    "18Ayaraltin": {
      "Alış": "4506.08",
      "Satış": "4510.28"
    },
    "22Ayarbilezik": {
      "Alış": "5629.52",
      "Satış": "5634.76"
    },
    "Ikibucukaltin": {
      "Alış": "98763.42",
      "Satış": "100338.32"
    },
    "Beslialtin": {
      "Alış": "199995.93",
      "Satış": "203889.44"
    },
    "Gremsealtin": {
      "Alış": "98763.42",
      "Satış": "101017.95"
    },
    "Resataltin": {
      "Alış": "40739.91",
      "Satış": "41766.44"
    },
    "Hamitaltin": {
      "Alış": "40739.91",
      "Satış": "41766.44"
    },
    "Gramplatin": {
      "Alış": "2993.05",
      "Satış": "3003.73"
    },
    "Grampaladyum": {
      "Alış": "2225.52",
      "Satış": "2252.94"
    }
  }
}