{
  "timestamp": "2026-01-26 14:30:02",
  "fiyatlar": {
    "Gramaltin": {
      "Alış": "7092.9",
      "Satış": "7093.77"
    },
    "Gumus": {
      "Alış": "151.56",
      "Satış": "151.67"
    },
    "Ons": {
      "Alış": "0",
      "Satış": "0"
    },
    "Gramhasaltin": {
      "Alış": "7057.43",
      "Satış": "7058.31"
    },
    "Ceyrekaltin": {
      "Alış": "11605.9",
      "Satış": "11872.38"
    },
    "Yarimaltin": {
      "Alış": "23139.26",
      "Satış": "23744.76"
    },
    "Tamaltin": {
      "Alış": "46423.6",
      "Satış": "47344.3"
    },
    "Cumhuriyetaltini": {
      "Alış": "48058",
      "Satış": "48785"
    },
    "Ataaltin": {
      "Alış": "47874.34",
      "Satış": "49087.03"
    },
    "14Ayaraltin": {
      "Alış": "4134.6",
      "Satış": "4139"
    },
    "18Ayaraltin": {
      "Alış": "5295.19",
      "Satış": "5300.82"
    },
    "22Ayarbilezik": {
      "Alış": "6615.36",
      "Satış": "6622.39"
    },
    "Ikibucukaltin": {
      "Alış": "116059.01",
      "Satış": "117925.05"
    },
    "Beslialtin": {
      "Alış": "235019.49",
      "Satış": "239626.04"
    },
    "Gremsealtin": {
      "Alış": "116059.01",
      "Satış": "118723.81"
    },
    "Resataltin": {
      "Alış": "47874.34",
      "Satış": "49087.03"
    },
    "Hamitaltin": {
      "Alış": "47874.34",
      "Satış": "49087.03"
    },
    "Gramplatin": {
      "Alış": "4026.69",
      "Satış": "4033.98"
    },
    "Grampaladyum": {
      "Alış": "2950.6",
      "Satış": "2964.55"
    }
  }
}