{
  "timestamp": "2025-11-13 13:54:02",
  "fiyatlar": {
    "Gramaltin": {
      "Alış": "5747.73",
      "Satış": "5748.49"
    },
    "Gumus": {
      "Alış": "73.31",
      "Satış": "73.4"
    },
    "Ons": {
      "Alış": "0",
      "Satış": "0"
    },
    "Gramhasaltin": {
      "Alış": "5718.99",
      "Satış": "5719.75"
    },
    "Ceyrekaltin": {
      "Alış": "9503.62",
      "Satış": "9720.75"
    },
    "Yarimaltin": {
      "Alış": "18947.83",
      "Satış": "19441.5"
    },
    "Tamaltin": {
      "Alış": "38014.46",
      "Satış": "38764.1"
    },
    "Cumhuriyetaltini": {
      "Alış": "39395",
      "Satış": "39990"
    },
    "Ataaltin": {
      "Alış": "39202.42",
      "Satış": "40191"
    },
    "14Ayaraltin": {
      "Alış": "3385.66",
      "Satış": "3388.89"
    },
    "18Ayaraltin": {
      "Alış": "4336.02",
      "Satış": "4340.15"
    },
    "22Ayarbilezik": {
      "Alış": "5417.06",
      "Satış": "5422.22"
    },
    "Ikibucukaltin": {
      "Alış": "95036.16",
      "Satış": "96553.52"
    },
    "Beslialtin": {
      "Alış": "192448.22",
      "Satış": "196198.66"
    },
    "Gremsealtin": {
      "Alış": "95036.16",
      "Satış": "97207.52"
    },
    "Resataltin": {
      "Alış": "39202.42",
      "Satış": "40191"
    },
    "Hamitaltin": {
      "Alış": "39202.42",
      "Satış": "40191"
    },
    "Gramplatin": {
      "Alış": "2200.45",
      "Satış": "2207.7"
    },
    "Grampaladyum": {
      "Alış": "2014.32",
      "Satış": "2025.05"
    }
  }
}