{
  "timestamp": "2026-03-18 02:17:02",
  "fiyatlar": {
    "Gramaltin": {
      "Alış": "7106.99",
      "Satış": "7107.87"
    },
    "Gumus": {
      "Alış": "112.37",
      "Satış": "112.51"
    },
    "Ons": {
      "Alış": "0",
      "Satış": "0"
    },
    "Gramhasaltin": {
      "Alış": "7071.45",
      "Satış": "7072.33"
    },
    "Ceyrekaltin": {
      "Alış": "11584.42",
      "Satış": "11857.76"
    },
    "Yarimaltin": {
      "Alış": "23096.45",
      "Satış": "23715.51"
    },
    "Tamaltin": {
      "Alış": "46337.7",
      "Satış": "47285.97"
    },
    "Cumhuriyetaltini": {
      "Alış": "48062",
      "Satış": "48778"
    },
    "Ataaltin": {
      "Alış": "47785.75",
      "Satış": "49026.56"
    },
    "14Ayaraltin": {
      "Alış": "4126.95",
      "Satış": "4133.9"
    },
    "18Ayaraltin": {
      "Alış": "5285.39",
      "Satış": "5294.29"
    },
    "22Ayarbilezik": {
      "Alış": "6603.12",
      "Satış": "6614.23"
    },
    "Ikibucukaltin": {
      "Alış": "115844.24",
      "Satış": "117779.79"
    },
    "Beslialtin": {
      "Alış": "234584.59",
      "Satış": "239330.85"
    },
    "Gremsealtin": {
      "Alış": "115844.24",
      "Satış": "118577.56"
    },
    "Resataltin": {
      "Alış": "47785.75",
      "Satış": "49026.56"
    },
    "Hamitaltin": {
      "Alış": "47785.75",
      "Satış": "49026.56"
    },
    "Gramplatin": {
      "Alış": "3009.88",
      "Satış": "3026.29"
    },
    "Grampaladyum": {
      "Alış": "2257.96",
      "Satış": "2273.64"
    }
  }
}