{
  "timestamp": "2025-09-12 14:33:01",
  "fiyatlar": {
    "Gramaltin": {
      "Alış": "4855.29",
      "Satış": "4855.74"
    },
    "Gumus": {
      "Alış": "56.19",
      "Satış": "56.25"
    },
    "Ons": {
      "Alış": "0",
      "Satış": "0"
    },
    "Gramhasaltin": {
      "Alış": "4831.01",
      "Satış": "4831.46"
    },
    "Ceyrekaltin": {
      "Alış": "7868.34",
      "Satış": "8047.75"
    },
    "Yarimaltin": {
      "Alış": "15687.51",
      "Satış": "16095.5"
    },
    "Tamaltin": {
      "Alış": "31473.37",
      "Satış": "32092.56"
    },
    "Cumhuriyetaltini": {
      "Alış": "32613",
      "Satış": "33106"
    },
    "Ataaltin": {
      "Alış": "32456.91",
      "Satış": "33273.88"
    },
    "14Ayaraltin": {
      "Alış": "2803.1",
      "Satış": "2805.64"
    },
    "18Ayaraltin": {
      "Alış": "3589.93",
      "Satış": "3593.19"
    },
    "22Ayarbilezik": {
      "Alış": "4484.96",
      "Satış": "4489.02"
    },
    "Ikibucukaltin": {
      "Alış": "78683.42",
      "Satış": "79936.07"
    },
    "Beslialtin": {
      "Alış": "159333.93",
      "Satış": "162431.68"
    },
    "Gremsealtin": {
      "Alış": "78683.42",
      "Satış": "80477.51"
    },
    "Resataltin": {
      "Alış": "32456.91",
      "Satış": "33273.88"
    },
    "Hamitaltin": {
      "Alış": "32456.91",
      "Satış": "33273.88"
    },
    "Gramplatin": {
      "Alış": "1860.56",
      "Satış": "1863.13"
    },
    "Grampaladyum": {
      "Alış": "1608.11",
      "Satış": "1614.49"
    }
  }
}