{
  "timestamp": "2026-04-07 00:47:02",
  "fiyatlar": {
    "Gramaltin": {
      "Alış": "6662.54",
      "Satış": "6663.94"
    },
    "Gumus": {
      "Alış": "104.25",
      "Satış": "104.35"
    },
    "Ons": {
      "Alış": "0",
      "Satış": "0"
    },
    "Gramhasaltin": {
      "Alış": "6629.22",
      "Satış": "6630.62"
    },
    "Ceyrekaltin": {
      "Alış": "10800.37",
      "Satış": "11053.73"
    },
    "Yarimaltin": {
      "Alış": "21533.24",
      "Satış": "22107.46"
    },
    "Tamaltin": {
      "Alış": "43201.48",
      "Satış": "44079.71"
    },
    "Cumhuriyetaltini": {
      "Alış": "44843",
      "Satış": "45520"
    },
    "Ataaltin": {
      "Alış": "44551.52",
      "Satış": "45702.27"
    },
    "14Ayaraltin": {
      "Alış": "3847.63",
      "Satış": "3853.59"
    },
    "18Ayaraltin": {
      "Alış": "4927.67",
      "Satış": "4935.3"
    },
    "22Ayarbilezik": {
      "Alış": "6156.21",
      "Satış": "6165.75"
    },
    "Ikibucukaltin": {
      "Alış": "108003.7",
      "Satış": "109793.62"
    },
    "Beslialtin": {
      "Alış": "218707.48",
      "Satış": "223102.8"
    },
    "Gremsealtin": {
      "Alış": "108003.7",
      "Satış": "110537.3"
    },
    "Resataltin": {
      "Alış": "44551.52",
      "Satış": "45702.27"
    },
    "Hamitaltin": {
      "Alış": "44551.52",
      "Satış": "45702.27"
    },
    "Gramplatin": {
      "Alış": "2834.56",
      "Satış": "2851.39"
    },
    "Grampaladyum": {
      "Alış": "2114.75",
      "Satış": "2142.43"
    }
  }
}