{
  "timestamp": "2026-02-10 01:53:02",
  "fiyatlar": {
    "Gramaltin": {
      "Alış": "7089.72",
      "Satış": "7090.93"
    },
    "Gumus": {
      "Alış": "116.69",
      "Satış": "116.81"
    },
    "Ons": {
      "Alış": "0",
      "Satış": "0"
    },
    "Gramhasaltin": {
      "Alış": "7054.27",
      "Satış": "7055.48"
    },
    "Ceyrekaltin": {
      "Alış": "11665.04",
      "Satış": "11961.59"
    },
    "Yarimaltin": {
      "Alış": "23257.18",
      "Satış": "23923.19"
    },
    "Tamaltin": {
      "Alış": "46660.18",
      "Satış": "47700.06"
    },
    "Cumhuriyetaltini": {
      "Alış": "48404",
      "Satış": "49144"
    },
    "Ataaltin": {
      "Alış": "48118.31",
      "Satış": "49455.89"
    },
    "14Ayaraltin": {
      "Alış": "4155.67",
      "Satış": "4170.1"
    },
    "18Ayaraltin": {
      "Alış": "5322.18",
      "Satış": "5340.65"
    },
    "22Ayarbilezik": {
      "Alış": "6649.08",
      "Satış": "6672.16"
    },
    "Ikibucukaltin": {
      "Alış": "116650.45",
      "Satış": "118811.19"
    },
    "Beslialtin": {
      "Alış": "236217.16",
      "Satış": "241426.68"
    },
    "Gremsealtin": {
      "Alış": "116650.45",
      "Satış": "119615.95"
    },
    "Resataltin": {
      "Alış": "48118.31",
      "Satış": "49455.89"
    },
    "Hamitaltin": {
      "Alış": "48118.31",
      "Satış": "49455.89"
    },
    "Gramplatin": {
      "Alış": "2971.09",
      "Satış": "2985.86"
    },
    "Grampaladyum": {
      "Alış": "2425.31",
      "Satış": "2453.26"
    }
  }
}