{
  "timestamp": "2025-11-18 00:30:02",
  "fiyatlar": {
    "Gramaltin": {
      "Alış": "5502.02",
      "Satış": "5502.83"
    },
    "Gumus": {
      "Alış": "68.24",
      "Satış": "68.29"
    },
    "Ons": {
      "Alış": "0",
      "Satış": "0"
    },
    "Gramhasaltin": {
      "Alış": "5474.51",
      "Satış": "5475.32"
    },
    "Ceyrekaltin": {
      "Alış": "9189.23",
      "Satış": "9399.42"
    },
    "Yarimaltin": {
      "Alış": "18321.02",
      "Satış": "18798.83"
    },
    "Tamaltin": {
      "Alış": "36756.9",
      "Satış": "37482.68"
    },
    "Cumhuriyetaltini": {
      "Alış": "38078",
      "Satış": "38653"
    },
    "Ataaltin": {
      "Alış": "37905.56",
      "Satış": "38862.42"
    },
    "14Ayaraltin": {
      "Alış": "3273.66",
      "Satış": "3276.86"
    },
    "18Ayaraltin": {
      "Alış": "4192.58",
      "Satış": "4196.68"
    },
    "22Ayarbilezik": {
      "Alış": "5237.86",
      "Satış": "5242.98"
    },
    "Ikibucukaltin": {
      "Alış": "91892.26",
      "Satış": "93361.78"
    },
    "Beslialtin": {
      "Alış": "186081.82",
      "Satış": "189712.97"
    },
    "Gremsealtin": {
      "Alış": "91892.26",
      "Satış": "93994.16"
    },
    "Resataltin": {
      "Alış": "37905.56",
      "Satış": "38862.42"
    },
    "Hamitaltin": {
      "Alış": "37905.56",
      "Satış": "38862.42"
    },
    "Gramplatin": {
      "Alış": "2084.33",
      "Satış": "2090.33"
    },
    "Grampaladyum": {
      "Alış": "1893.22",
      "Satış": "1898.66"
    }
  }
}