{
  "timestamp": "2026-01-27 12:24:02",
  "fiyatlar": {
    "Gramaltin": {
      "Alış": "7097.42",
      "Satış": "7098.3"
    },
    "Gumus": {
      "Alış": "156.71",
      "Satış": "156.81"
    },
    "Ons": {
      "Alış": "0",
      "Satış": "0"
    },
    "Gramhasaltin": {
      "Alış": "7061.94",
      "Satış": "7062.81"
    },
    "Ceyrekaltin": {
      "Alış": "11693.44",
      "Satış": "11959.12"
    },
    "Yarimaltin": {
      "Alış": "23313.79",
      "Satış": "23918.24"
    },
    "Tamaltin": {
      "Alış": "46773.75",
      "Satış": "47690.19"
    },
    "Cumhuriyetaltini": {
      "Alış": "48470",
      "Satış": "49201"
    },
    "Ataaltin": {
      "Alış": "48235.43",
      "Satış": "49445.66"
    },
    "14Ayaraltin": {
      "Alış": "4165.79",
      "Satış": "4169.23"
    },
    "18Ayaraltin": {
      "Alış": "5335.13",
      "Satış": "5339.55"
    },
    "22Ayarbilezik": {
      "Alış": "6665.26",
      "Satış": "6670.78"
    },
    "Ikibucukaltin": {
      "Alış": "116934.37",
      "Satış": "118786.62"
    },
    "Beslialtin": {
      "Alış": "236792.1",
      "Satış": "241376.75"
    },
    "Gremsealtin": {
      "Alış": "116934.37",
      "Satış": "119591.21"
    },
    "Resataltin": {
      "Alış": "48235.43",
      "Satış": "49445.66"
    },
    "Hamitaltin": {
      "Alış": "48235.43",
      "Satış": "49445.66"
    },
    "Gramplatin": {
      "Alış": "3783.93",
      "Satış": "3790.86"
    },
    "Grampaladyum": {
      "Alış": "2845.35",
      "Satış": "2851.56"
    }
  }
}