{
  "timestamp": "2026-03-09 16:36:02",
  "fiyatlar": {
    "Gramaltin": {
      "Alış": "7237.16",
      "Satış": "7238.08"
    },
    "Gumus": {
      "Alış": "120.1",
      "Satış": "120.2"
    },
    "Ons": {
      "Alış": "0",
      "Satış": "0"
    },
    "Gramhasaltin": {
      "Alış": "7200.97",
      "Satış": "7201.89"
    },
    "Ceyrekaltin": {
      "Alış": "11733.7",
      "Satış": "12010.31"
    },
    "Yarimaltin": {
      "Alış": "23394.07",
      "Satış": "24020.62"
    },
    "Tamaltin": {
      "Alış": "46934.8",
      "Satış": "47894.33"
    },
    "Cumhuriyetaltini": {
      "Alış": "48666",
      "Satış": "49403"
    },
    "Ataaltin": {
      "Alış": "48401.52",
      "Satış": "49657.31"
    },
    "14Ayaraltin": {
      "Alış": "4180.13",
      "Satış": "4187.08"
    },
    "18Ayaraltin": {
      "Alış": "5353.5",
      "Satış": "5362.4"
    },
    "22Ayarbilezik": {
      "Alış": "6688.21",
      "Satış": "6699.33"
    },
    "Ikibucukaltin": {
      "Alış": "117337.01",
      "Satış": "119295.08"
    },
    "Beslialtin": {
      "Alış": "237607.44",
      "Satış": "242409.95"
    },
    "Gremsealtin": {
      "Alış": "117337.01",
      "Satış": "120103.11"
    },
    "Resataltin": {
      "Alış": "48401.52",
      "Satış": "49657.31"
    },
    "Hamitaltin": {
      "Alış": "48401.52",
      "Satış": "49657.31"
    },
    "Gramplatin": {
      "Alış": "3058.38",
      "Satış": "3064.52"
    },
    "Grampaladyum": {
      "Alış": "2330.81",
      "Satış": "2335.65"
    }
  }
}