{
  "timestamp": "2025-09-29 14:27:02",
  "fiyatlar": {
    "Gramaltin": {
      "Alış": "5103.87",
      "Satış": "5104.48"
    },
    "Gumus": {
      "Alış": "62.8",
      "Satış": "62.84"
    },
    "Ons": {
      "Alış": "0",
      "Satış": "0"
    },
    "Gramhasaltin": {
      "Alış": "5078.32",
      "Satış": "5078.92"
    },
    "Ceyrekaltin": {
      "Alış": "8349.07",
      "Satış": "8542.64"
    },
    "Yarimaltin": {
      "Alış": "16645.95",
      "Satış": "17085.28"
    },
    "Tamaltin": {
      "Alış": "33396.27",
      "Satış": "34066.05"
    },
    "Cumhuriyetaltini": {
      "Alış": "34628",
      "Satış": "35153"
    },
    "Ataaltin": {
      "Alış": "34439.9",
      "Satış": "35320.02"
    },
    "14Ayaraltin": {
      "Alış": "2974.36",
      "Satış": "2978.17"
    },
    "18Ayaraltin": {
      "Alış": "3809.26",
      "Satış": "3814.14"
    },
    "22Ayarbilezik": {
      "Alış": "4758.97",
      "Satış": "4765.07"
    },
    "Ikibucukaltin": {
      "Alış": "83490.67",
      "Satış": "84851.65"
    },
    "Beslialtin": {
      "Alış": "169068.61",
      "Satış": "172420.22"
    },
    "Gremsealtin": {
      "Alış": "83490.67",
      "Satış": "85426.38"
    },
    "Resataltin": {
      "Alış": "34439.9",
      "Satış": "35320.02"
    },
    "Hamitaltin": {
      "Alış": "34439.9",
      "Satış": "35320.02"
    },
    "Gramplatin": {
      "Alış": "2138.35",
      "Satış": "2141.95"
    },
    "Grampaladyum": {
      "Alış": "1713.64",
      "Satış": "1718.86"
    }
  }
}