{
  "timestamp": "2026-04-14 19:38:03",
  "fiyatlar": {
    "Gramaltin": {
      "Alış": "6925.58",
      "Satış": "6926.43"
    },
    "Gumus": {
      "Alış": "114.1",
      "Satış": "114.2"
    },
    "Ons": {
      "Alış": "0",
      "Satış": "0"
    },
    "Gramhasaltin": {
      "Alış": "6890.95",
      "Satış": "6891.8"
    },
    "Ceyrekaltin": {
      "Alış": "11009.25",
      "Satış": "11262.46"
    },
    "Yarimaltin": {
      "Alış": "21949.69",
      "Satış": "22524.92"
    },
    "Tamaltin": {
      "Alış": "44037",
      "Satış": "44912.07"
    },
    "Cumhuriyetaltini": {
      "Alış": "45605",
      "Satış": "46290"
    },
    "Ataaltin": {
      "Alış": "45413.16",
      "Satış": "46565.27"
    },
    "14Ayaraltin": {
      "Alış": "3922.05",
      "Satış": "3926.36"
    },
    "18Ayaraltin": {
      "Alış": "5022.97",
      "Satış": "5028.5"
    },
    "22Ayarbilezik": {
      "Alış": "6275.27",
      "Satış": "6282.18"
    },
    "Ikibucukaltin": {
      "Alış": "110092.51",
      "Satış": "111866.87"
    },
    "Beslialtin": {
      "Alış": "222937.34",
      "Satış": "227315.68"
    },
    "Gremsealtin": {
      "Alış": "110092.51",
      "Satış": "112624.59"
    },
    "Resataltin": {
      "Alış": "45413.16",
      "Satış": "46565.27"
    },
    "Hamitaltin": {
      "Alış": "45413.16",
      "Satış": "46565.27"
    },
    "Gramplatin": {
      "Alış": "3010.15",
      "Satış": "3018.06"
    },
    "Grampaladyum": {
      "Alış": "2274.41",
      "Satış": "2283.09"
    }
  }
}