{
  "timestamp": "2026-04-21 12:49:03",
  "fiyatlar": {
    "Gramaltin": {
      "Alış": "6905.05",
      "Satış": "6905.93"
    },
    "Gumus": {
      "Alış": "113.77",
      "Satış": "113.85"
    },
    "Ons": {
      "Alış": "0",
      "Satış": "0"
    },
    "Gramhasaltin": {
      "Alış": "6870.52",
      "Satış": "6871.4"
    },
    "Ceyrekaltin": {
      "Alış": "11037.08",
      "Satış": "11288.4"
    },
    "Yarimaltin": {
      "Alış": "22005.17",
      "Satış": "22576.8"
    },
    "Tamaltin": {
      "Alış": "44148.3",
      "Satış": "45015.52"
    },
    "Cumhuriyetaltini": {
      "Alış": "45748",
      "Satış": "46442"
    },
    "Ataaltin": {
      "Alış": "45527.94",
      "Satış": "46672.53"
    },
    "14Ayaraltin": {
      "Alış": "3931.96",
      "Satış": "3935.41"
    },
    "18Ayaraltin": {
      "Alış": "5035.67",
      "Satış": "5040.08"
    },
    "22Ayarbilezik": {
      "Alış": "6291.13",
      "Satış": "6296.65"
    },
    "Ikibucukaltin": {
      "Alış": "110370.75",
      "Satış": "112124.55"
    },
    "Beslialtin": {
      "Alış": "223500.77",
      "Satış": "227839.29"
    },
    "Gremsealtin": {
      "Alış": "110370.75",
      "Satış": "112884.01"
    },
    "Resataltin": {
      "Alış": "45527.94",
      "Satış": "46672.53"
    },
    "Hamitaltin": {
      "Alış": "45527.94",
      "Satış": "46672.53"
    },
    "Gramplatin": {
      "Alış": "2983.19",
      "Satış": "2990.55"
    },
    "Grampaladyum": {
      "Alış": "2245.04",
      "Satış": "2254.83"
    }
  }
}