{
  "timestamp": "2025-10-30 13:37:02",
  "fiyatlar": {
    "Gramaltin": {
      "Alış": "5379.2",
      "Satış": "5379.92"
    },
    "Gumus": {
      "Alış": "64.59",
      "Satış": "64.65"
    },
    "Ons": {
      "Alış": "0",
      "Satış": "0"
    },
    "Gramhasaltin": {
      "Alış": "5352.31",
      "Satış": "5353.02"
    },
    "Ceyrekaltin": {
      "Alış": "9008.29",
      "Satış": "9214.43"
    },
    "Yarimaltin": {
      "Alış": "17960.28",
      "Satış": "18428.86"
    },
    "Tamaltin": {
      "Alış": "36033.16",
      "Satış": "36745.01"
    },
    "Cumhuriyetaltini": {
      "Alış": "37490",
      "Satış": "38057"
    },
    "Ataaltin": {
      "Alış": "37159.19",
      "Satış": "38097.58"
    },
    "14Ayaraltin": {
      "Alış": "3209.2",
      "Satış": "3212.37"
    },
    "18Ayaraltin": {
      "Alış": "4110.03",
      "Satış": "4114.09"
    },
    "22Ayarbilezik": {
      "Alış": "5134.73",
      "Satış": "5139.79"
    },
    "Ikibucukaltin": {
      "Alış": "90082.9",
      "Satış": "91524.37"
    },
    "Beslialtin": {
      "Alış": "182417.86",
      "Satış": "185979.32"
    },
    "Gremsealtin": {
      "Alış": "90082.9",
      "Satış": "92144.3"
    },
    "Resataltin": {
      "Alış": "37159.19",
      "Satış": "38097.58"
    },
    "Hamitaltin": {
      "Alış": "37159.19",
      "Satış": "38097.58"
    },
    "Gramplatin": {
      "Alış": "2154.23",
      "Satış": "2160.17"
    },
    "Grampaladyum": {
      "Alış": "1927.95",
      "Satış": "1933.82"
    }
  }
}