{
  "timestamp": "2026-02-05 16:10:02",
  "fiyatlar": {
    "Gramaltin": {
      "Alış": "6744.39",
      "Satış": "6746.85"
    },
    "Gumus": {
      "Alış": "106.81",
      "Satış": "106.95"
    },
    "Ons": {
      "Alış": "0",
      "Satış": "0"
    },
    "Gramhasaltin": {
      "Alış": "6710.67",
      "Satış": "6713.12"
    },
    "Ceyrekaltin": {
      "Alış": "11633.01",
      "Satış": "11926.03"
    },
    "Yarimaltin": {
      "Alış": "23193.32",
      "Satış": "23852.05"
    },
    "Tamaltin": {
      "Alış": "46532.05",
      "Satış": "47558.22"
    },
    "Cumhuriyetaltini": {
      "Alış": "47470",
      "Satış": "48366"
    },
    "Ataaltin": {
      "Alış": "47986.18",
      "Satış": "49308.83"
    },
    "14Ayaraltin": {
      "Alış": "4144.26",
      "Satış": "4157.7"
    },
    "18Ayaraltin": {
      "Alış": "5307.56",
      "Satış": "5324.77"
    },
    "22Ayarbilezik": {
      "Alış": "6630.82",
      "Satış": "6652.32"
    },
    "Ikibucukaltin": {
      "Alış": "116330.13",
      "Satış": "118457.91"
    },
    "Beslialtin": {
      "Alış": "235568.51",
      "Satış": "240708.8"
    },
    "Gremsealtin": {
      "Alış": "116330.13",
      "Satış": "119260.27"
    },
    "Resataltin": {
      "Alış": "47986.18",
      "Satış": "49308.83"
    },
    "Hamitaltin": {
      "Alış": "47986.18",
      "Satış": "49308.83"
    },
    "Gramplatin": {
      "Alış": "2866.15",
      "Satış": "2877.99"
    },
    "Grampaladyum": {
      "Alış": "2380.23",
      "Satış": "2390.4"
    }
  }
}