{
  "timestamp": "2025-10-17 08:52:01",
  "fiyatlar": {
    "Gramaltin": {
      "Alış": "5879.62",
      "Satış": "5880.36"
    },
    "Gumus": {
      "Alış": "73.36",
      "Satış": "73.44"
    },
    "Ons": {
      "Alış": "0",
      "Satış": "0"
    },
    "Gramhasaltin": {
      "Alış": "5850.22",
      "Satış": "5850.96"
    },
    "Ceyrekaltin": {
      "Alış": "9693.42",
      "Satış": "9917.08"
    },
    "Yarimaltin": {
      "Alış": "19326.26",
      "Satış": "19834.16"
    },
    "Tamaltin": {
      "Alış": "38773.68",
      "Satış": "39547.01"
    },
    "Cumhuriyetaltini": {
      "Alış": "40074",
      "Satış": "40680"
    },
    "Ataaltin": {
      "Alış": "39985.36",
      "Satış": "41002.73"
    },
    "14Ayaraltin": {
      "Alış": "3453.28",
      "Satış": "3457.33"
    },
    "18Ayaraltin": {
      "Alış": "4422.62",
      "Satış": "4427.81"
    },
    "22Ayarbilezik": {
      "Alış": "5525.25",
      "Satış": "5531.73"
    },
    "Ikibucukaltin": {
      "Alış": "96934.21",
      "Satış": "98503.61"
    },
    "Beslialtin": {
      "Alış": "196291.77",
      "Satış": "200161.27"
    },
    "Gremsealtin": {
      "Alış": "96934.21",
      "Satış": "99170.81"
    },
    "Resataltin": {
      "Alış": "39985.36",
      "Satış": "41002.73"
    },
    "Hamitaltin": {
      "Alış": "39985.36",
      "Satış": "41002.73"
    },
    "Gramplatin": {
      "Alış": "2305.05",
      "Satış": "2309.43"
    },
    "Grampaladyum": {
      "Alış": "2176.86",
      "Satış": "2186.03"
    }
  }
}