{
  "timestamp": "2026-03-06 20:56:02",
  "fiyatlar": {
    "Gramaltin": {
      "Alış": "7276.58",
      "Satış": "7277.52"
    },
    "Gumus": {
      "Alış": "118.87",
      "Satış": "119.02"
    },
    "Ons": {
      "Alış": "0",
      "Satış": "0"
    },
    "Gramhasaltin": {
      "Alış": "7240.2",
      "Satış": "7241.13"
    },
    "Ceyrekaltin": {
      "Alış": "11854.23",
      "Satış": "12152.52"
    },
    "Yarimaltin": {
      "Alış": "23634.37",
      "Satış": "24305.04"
    },
    "Tamaltin": {
      "Alış": "47416.91",
      "Satış": "48461.43"
    },
    "Cumhuriyetaltini": {
      "Alış": "48907",
      "Satış": "49663"
    },
    "Ataaltin": {
      "Alış": "48898.69",
      "Satış": "50245.28"
    },
    "14Ayaraltin": {
      "Alış": "4223.07",
      "Satış": "4236.66"
    },
    "18Ayaraltin": {
      "Alış": "5408.49",
      "Satış": "5425.9"
    },
    "22Ayarbilezik": {
      "Alış": "6756.91",
      "Satış": "6778.65"
    },
    "Ikibucukaltin": {
      "Alış": "118542.27",
      "Satış": "120707.6"
    },
    "Beslialtin": {
      "Alış": "240048.1",
      "Satış": "245280.22"
    },
    "Gremsealtin": {
      "Alış": "118542.27",
      "Satış": "121525.2"
    },
    "Resataltin": {
      "Alış": "48898.69",
      "Satış": "50245.28"
    },
    "Hamitaltin": {
      "Alış": "48898.69",
      "Satış": "50245.28"
    },
    "Gramplatin": {
      "Alış": "3016.99",
      "Satış": "3022.44"
    },
    "Grampaladyum": {
      "Alış": "2318.35",
      "Satış": "2326.58"
    }
  }
}