{
  "timestamp": "2025-09-19 12:43:02",
  "fiyatlar": {
    "Gramaltin": {
      "Alış": "4868.46",
      "Satış": "4868.95"
    },
    "Gumus": {
      "Alış": "56.23",
      "Satış": "56.29"
    },
    "Ons": {
      "Alış": "0",
      "Satış": "0"
    },
    "Gramhasaltin": {
      "Alış": "4844.12",
      "Satış": "4844.61"
    },
    "Ceyrekaltin": {
      "Alış": "7942.88",
      "Satış": "8139.69"
    },
    "Yarimaltin": {
      "Alış": "15836.12",
      "Satış": "16279.37"
    },
    "Tamaltin": {
      "Alış": "31771.53",
      "Satış": "32459.18"
    },
    "Cumhuriyetaltini": {
      "Alış": "32937",
      "Satış": "33435"
    },
    "Ataaltin": {
      "Alış": "32764.39",
      "Satış": "33654"
    },
    "14Ayaraltin": {
      "Alış": "2829.65",
      "Satış": "2837.69"
    },
    "18Ayaraltin": {
      "Alış": "3623.94",
      "Satış": "3634.23"
    },
    "22Ayarbilezik": {
      "Alış": "4527.44",
      "Satış": "4540.3"
    },
    "Ikibucukaltin": {
      "Alış": "79428.83",
      "Satış": "80849.25"
    },
    "Beslialtin": {
      "Alış": "160843.38",
      "Satış": "164287.27"
    },
    "Gremsealtin": {
      "Alış": "79428.83",
      "Satış": "81396.87"
    },
    "Resataltin": {
      "Alış": "32764.39",
      "Satış": "33654"
    },
    "Hamitaltin": {
      "Alış": "32764.39",
      "Satış": "33654"
    },
    "Gramplatin": {
      "Alış": "1849.44",
      "Satış": "1853.34"
    },
    "Grampaladyum": {
      "Alış": "1536.92",
      "Satış": "1542.19"
    }
  }
}