{
  "timestamp": "2025-09-19 14:52:02",
  "fiyatlar": {
    "Gramaltin": {
      "Alış": "4859.07",
      "Satış": "4859.56"
    },
    "Gumus": {
      "Alış": "56.08",
      "Satış": "56.14"
    },
    "Ons": {
      "Alış": "0",
      "Satış": "0"
    },
    "Gramhasaltin": {
      "Alış": "4834.77",
      "Satış": "4835.26"
    },
    "Ceyrekaltin": {
      "Alış": "7960.78",
      "Satış": "8142.26"
    },
    "Yarimaltin": {
      "Alış": "15871.81",
      "Satış": "16284.51"
    },
    "Tamaltin": {
      "Alış": "31843.13",
      "Satış": "32469.43"
    },
    "Cumhuriyetaltini": {
      "Alış": "32974",
      "Satış": "33472"
    },
    "Ataaltin": {
      "Alış": "32838.23",
      "Satış": "33664.62"
    },
    "14Ayaraltin": {
      "Alış": "2836.03",
      "Satış": "2838.59"
    },
    "18Ayaraltin": {
      "Alış": "3632.11",
      "Satış": "3635.38"
    },
    "22Ayarbilezik": {
      "Alış": "4537.65",
      "Satış": "4541.74"
    },
    "Ikibucukaltin": {
      "Alış": "79607.82",
      "Satış": "80874.78"
    },
    "Beslialtin": {
      "Alış": "161205.84",
      "Satış": "164339.14"
    },
    "Gremsealtin": {
      "Alış": "79607.82",
      "Satış": "81422.57"
    },
    "Resataltin": {
      "Alış": "32838.23",
      "Satış": "33664.62"
    },
    "Hamitaltin": {
      "Alış": "32838.23",
      "Satış": "33664.62"
    },
    "Gramplatin": {
      "Alış": "1844.98",
      "Satış": "1849.64"
    },
    "Grampaladyum": {
      "Alış": "1539.61",
      "Satış": "1545.29"
    }
  }
}