{
  "timestamp": "2026-03-11 01:27:02",
  "fiyatlar": {
    "Gramaltin": {
      "Alış": "7365.72",
      "Satış": "7366.87"
    },
    "Gumus": {
      "Alış": "125.95",
      "Satış": "126.09"
    },
    "Ons": {
      "Alış": "0",
      "Satış": "0"
    },
    "Gramhasaltin": {
      "Alış": "7328.89",
      "Satış": "7330.04"
    },
    "Ceyrekaltin": {
      "Alış": "11864.39",
      "Satış": "12141.13"
    },
    "Yarimaltin": {
      "Alış": "23654.62",
      "Satış": "24282.26"
    },
    "Tamaltin": {
      "Alış": "47457.55",
      "Satış": "48416.01"
    },
    "Cumhuriyetaltini": {
      "Alış": "49196",
      "Satış": "49933"
    },
    "Ataaltin": {
      "Alış": "48940.6",
      "Satış": "50198.2"
    },
    "14Ayaraltin": {
      "Alış": "4226.69",
      "Satış": "4232.69"
    },
    "18Ayaraltin": {
      "Alış": "5413.13",
      "Satış": "5420.81"
    },
    "22Ayarbilezik": {
      "Alış": "6762.7",
      "Satış": "6772.3"
    },
    "Ikibucukaltin": {
      "Alış": "118643.87",
      "Satış": "120594.49"
    },
    "Beslialtin": {
      "Alış": "240253.84",
      "Satış": "245050.38"
    },
    "Gremsealtin": {
      "Alış": "118643.87",
      "Satış": "121411.32"
    },
    "Resataltin": {
      "Alış": "48940.6",
      "Satış": "50198.2"
    },
    "Hamitaltin": {
      "Alış": "48940.6",
      "Satış": "50198.2"
    },
    "Gramplatin": {
      "Alış": "3122.59",
      "Satış": "3135.46"
    },
    "Grampaladyum": {
      "Alış": "2343.89",
      "Satış": "2374.29"
    }
  }
}