{
  "timestamp": "2026-04-30 16:48:03",
  "fiyatlar": {
    "Gramaltin": {
      "Alış": "6706.97",
      "Satış": "6707.86"
    },
    "Gumus": {
      "Alış": "105.93",
      "Satış": "106.03"
    },
    "Ons": {
      "Alış": "0",
      "Satış": "0"
    },
    "Gramhasaltin": {
      "Alış": "6673.44",
      "Satış": "6674.32"
    },
    "Ceyrekaltin": {
      "Alış": "10685.66",
      "Satış": "10929.23"
    },
    "Yarimaltin": {
      "Alış": "21304.54",
      "Satış": "21858.46"
    },
    "Tamaltin": {
      "Alış": "42742.66",
      "Satış": "43583.22"
    },
    "Cumhuriyetaltini": {
      "Alış": "44408",
      "Satış": "45078"
    },
    "Ataaltin": {
      "Alış": "44078.36",
      "Satış": "45187.51"
    },
    "14Ayaraltin": {
      "Alış": "3806.77",
      "Satış": "3810.19"
    },
    "18Ayaraltin": {
      "Alış": "4875.33",
      "Satış": "4879.72"
    },
    "22Ayarbilezik": {
      "Alış": "6090.83",
      "Satış": "6096.3"
    },
    "Ikibucukaltin": {
      "Alış": "106856.64",
      "Satış": "108556.98"
    },
    "Beslialtin": {
      "Alış": "216384.7",
      "Satış": "220589.92"
    },
    "Gremsealtin": {
      "Alış": "106856.64",
      "Satış": "109292.28"
    },
    "Resataltin": {
      "Alış": "44078.36",
      "Satış": "45187.51"
    },
    "Hamitaltin": {
      "Alış": "44078.36",
      "Satış": "45187.51"
    },
    "Gramplatin": {
      "Alış": "2842.43",
      "Satış": "2850.45"
    },
    "Grampaladyum": {
      "Alış": "2146.56",
      "Satış": "2154.45"
    }
  }
}