{
  "timestamp": "2025-08-26 02:29:03",
  "fiyatlar": {
    "Gramaltin": {
      "Alış": "4431.64",
      "Satış": "4432.09"
    },
    "Gumus": {
      "Alış": "50.77",
      "Satış": "50.82"
    },
    "Ons": {
      "Alış": "0",
      "Satış": "0"
    },
    "Gramhasaltin": {
      "Alış": "4409.48",
      "Satış": "4409.93"
    },
    "Ceyrekaltin": {
      "Alış": "7113.27",
      "Satış": "7275.79"
    },
    "Yarimaltin": {
      "Alış": "14182.09",
      "Satış": "14551.59"
    },
    "Tamaltin": {
      "Alış": "28453.09",
      "Satış": "29014.17"
    },
    "Cumhuriyetaltini": {
      "Alış": "29450",
      "Satış": "29895"
    },
    "Ataaltin": {
      "Alış": "29342.25",
      "Satış": "30082.18"
    },
    "14Ayaraltin": {
      "Alış": "2534.1",
      "Satış": "2536.51"
    },
    "18Ayaraltin": {
      "Alış": "3245.43",
      "Satış": "3248.52"
    },
    "22Ayarbilezik": {
      "Alış": "4054.57",
      "Satış": "4058.42"
    },
    "Ikibucukaltin": {
      "Alış": "71132.74",
      "Satış": "72268.42"
    },
    "Beslialtin": {
      "Alış": "144043.79",
      "Satış": "146850.86"
    },
    "Gremsealtin": {
      "Alış": "71132.74",
      "Satış": "72757.93"
    },
    "Resataltin": {
      "Alış": "29342.25",
      "Satış": "30082.18"
    },
    "Hamitaltin": {
      "Alış": "29342.25",
      "Satış": "30082.18"
    },
    "Gramplatin": {
      "Alış": "1767.7",
      "Satış": "1773.79"
    },
    "Grampaladyum": {
      "Alış": "1442.9",
      "Satış": "1449.89"
    }
  }
}