{
  "timestamp": "2026-05-04 00:07:02",
  "fiyatlar": {
    "Gramaltin": {
      "Alış": "6699.77",
      "Satış": "6700.6"
    },
    "Gumus": {
      "Alış": "109.33",
      "Satış": "109.47"
    },
    "Ons": {
      "Alış": "0",
      "Satış": "0"
    },
    "Gramhasaltin": {
      "Alış": "6666.28",
      "Satış": "6667.1"
    },
    "Ceyrekaltin": {
      "Alış": "10657.25",
      "Satış": "10902.6"
    },
    "Yarimaltin": {
      "Alış": "21247.89",
      "Satış": "21805.19"
    },
    "Tamaltin": {
      "Alış": "42628.99",
      "Satış": "43477.02"
    },
    "Cumhuriyetaltini": {
      "Alış": "44303",
      "Satış": "44973"
    },
    "Ataaltin": {
      "Alış": "43961.14",
      "Satış": "45077.4"
    },
    "14Ayaraltin": {
      "Alış": "3796.64",
      "Satış": "3800.91"
    },
    "18Ayaraltin": {
      "Alış": "4862.37",
      "Satış": "4867.83"
    },
    "22Ayarbilezik": {
      "Alış": "6074.63",
      "Satış": "6081.45"
    },
    "Ikibucukaltin": {
      "Alış": "106572.46",
      "Satış": "108292.46"
    },
    "Beslialtin": {
      "Alış": "215809.24",
      "Satış": "220052.42"
    },
    "Gremsealtin": {
      "Alış": "106572.46",
      "Satış": "109025.97"
    },
    "Resataltin": {
      "Alış": "43961.14",
      "Satış": "45077.4"
    },
    "Hamitaltin": {
      "Alış": "43961.14",
      "Satış": "45077.4"
    },
    "Gramplatin": {
      "Alış": "2852.1",
      "Satış": "2929.29"
    },
    "Grampaladyum": {
      "Alış": "2160.46",
      "Satış": "2267.89"
    }
  }
}