{
  "timestamp": "2026-01-06 13:14:02",
  "fiyatlar": {
    "Gramaltin": {
      "Alış": "6156.91",
      "Satış": "6157.68"
    },
    "Gumus": {
      "Alış": "107.61",
      "Satış": "107.67"
    },
    "Ons": {
      "Alış": "0",
      "Satış": "0"
    },
    "Gramhasaltin": {
      "Alış": "6126.12",
      "Satış": "6126.89"
    },
    "Ceyrekaltin": {
      "Alış": "10126.54",
      "Satış": "10359.94"
    },
    "Yarimaltin": {
      "Alış": "20189.78",
      "Satış": "20719.88"
    },
    "Tamaltin": {
      "Alış": "40506.15",
      "Satış": "41313.03"
    },
    "Cumhuriyetaltini": {
      "Alış": "42005",
      "Satış": "42639"
    },
    "Ataaltin": {
      "Alış": "41771.97",
      "Satış": "42833.75"
    },
    "14Ayaraltin": {
      "Alış": "3607.58",
      "Satış": "3611.72"
    },
    "18Ayaraltin": {
      "Alış": "4620.23",
      "Satış": "4625.54"
    },
    "22Ayarbilezik": {
      "Alış": "5772.13",
      "Satış": "5778.75"
    },
    "Ikibucukaltin": {
      "Alış": "101265.38",
      "Satış": "102902.39"
    },
    "Beslialtin": {
      "Alış": "205062.39",
      "Satış": "209099.68"
    },
    "Gremsealtin": {
      "Alış": "101265.38",
      "Satış": "103599.39"
    },
    "Resataltin": {
      "Alış": "41771.97",
      "Satış": "42833.75"
    },
    "Hamitaltin": {
      "Alış": "41771.97",
      "Satış": "42833.75"
    },
    "Gramplatin": {
      "Alış": "3174.21",
      "Satış": "3182.23"
    },
    "Grampaladyum": {
      "Alış": "2372.64",
      "Satış": "2382.75"
    }
  }
}