{
  "timestamp": "2025-08-29 16:52:02",
  "fiyatlar": {
    "Gramaltin": {
      "Alış": "4526.19",
      "Satış": "4526.62"
    },
    "Gumus": {
      "Alış": "51.52",
      "Satış": "51.57"
    },
    "Ons": {
      "Alış": "0",
      "Satış": "0"
    },
    "Gramhasaltin": {
      "Alış": "4503.56",
      "Satış": "4503.98"
    },
    "Ceyrekaltin": {
      "Alış": "7221.06",
      "Satış": "7384.19"
    },
    "Yarimaltin": {
      "Alış": "14396.99",
      "Satış": "14768.38"
    },
    "Tamaltin": {
      "Alış": "28884.24",
      "Satış": "29446.44"
    },
    "Cumhuriyetaltini": {
      "Alış": "29910",
      "Satış": "30362"
    },
    "Ataaltin": {
      "Alış": "29786.88",
      "Satış": "30530.36"
    },
    "14Ayaraltin": {
      "Alış": "2572.5",
      "Satış": "2574.31"
    },
    "18Ayaraltin": {
      "Alış": "3294.61",
      "Satış": "3296.92"
    },
    "22Ayarbilezik": {
      "Alış": "4116",
      "Satış": "4118.89"
    },
    "Ikibucukaltin": {
      "Alış": "72210.61",
      "Satış": "73345.12"
    },
    "Beslialtin": {
      "Alış": "146226.48",
      "Satış": "149038.73"
    },
    "Gremsealtin": {
      "Alış": "72210.61",
      "Satış": "73841.91"
    },
    "Resataltin": {
      "Alış": "29786.88",
      "Satış": "30530.36"
    },
    "Hamitaltin": {
      "Alış": "29786.88",
      "Satış": "30530.36"
    },
    "Gramplatin": {
      "Alış": "1788.14",
      "Satış": "1793.64"
    },
    "Grampaladyum": {
      "Alış": "1445.8",
      "Satış": "1450.02"
    }
  }
}