{
  "timestamp": "2025-12-25 13:13:02",
  "fiyatlar": {
    "Gramaltin": {
      "Alış": "6169.13",
      "Satış": "6170.05"
    },
    "Gumus": {
      "Alış": "98.82",
      "Satış": "99.07"
    },
    "Ons": {
      "Alış": "0",
      "Satış": "0"
    },
    "Gramhasaltin": {
      "Alış": "6138.28",
      "Satış": "6139.2"
    },
    "Ceyrekaltin": {
      "Alış": "9992.37",
      "Satış": "10220.38"
    },
    "Yarimaltin": {
      "Alış": "19922.29",
      "Satış": "20440.77"
    },
    "Tamaltin": {
      "Alış": "39969.49",
      "Satış": "40756.51"
    },
    "Cumhuriyetaltini": {
      "Alış": "41422",
      "Satış": "42051"
    },
    "Ataaltin": {
      "Alış": "41218.54",
      "Satış": "42256.75"
    },
    "14Ayaraltin": {
      "Alış": "3559.78",
      "Satış": "3563.07"
    },
    "18Ayaraltin": {
      "Alış": "4559.02",
      "Satış": "4563.23"
    },
    "22Ayarbilezik": {
      "Alış": "5695.65",
      "Satış": "5700.91"
    },
    "Ikibucukaltin": {
      "Alış": "99923.73",
      "Satış": "101516.22"
    },
    "Beslialtin": {
      "Alış": "202345.55",
      "Satış": "206282.97"
    },
    "Gremsealtin": {
      "Alış": "99923.73",
      "Satış": "102203.83"
    },
    "Resataltin": {
      "Alış": "41218.54",
      "Satış": "42256.75"
    },
    "Hamitaltin": {
      "Alış": "41218.54",
      "Satış": "42256.75"
    },
    "Gramplatin": {
      "Alış": "3103.71",
      "Satış": "3113.15"
    },
    "Grampaladyum": {
      "Alış": "2353.96",
      "Satış": "2389.29"
    }
  }
}