{
  "timestamp": "2025-12-11 17:16:02",
  "fiyatlar": {
    "Gramaltin": {
      "Alış": "5781.44",
      "Satış": "5782.2"
    },
    "Gumus": {
      "Alış": "85.51",
      "Satış": "85.58"
    },
    "Ons": {
      "Alış": "0",
      "Satış": "0"
    },
    "Gramhasaltin": {
      "Alış": "5752.53",
      "Satış": "5753.29"
    },
    "Ceyrekaltin": {
      "Alış": "9294.85",
      "Satış": "9507.4"
    },
    "Yarimaltin": {
      "Alış": "18531.61",
      "Satış": "19014.81"
    },
    "Tamaltin": {
      "Alış": "37179.4",
      "Satış": "37913.32"
    },
    "Cumhuriyetaltini": {
      "Alış": "38554",
      "Satış": "39135"
    },
    "Ataaltin": {
      "Alış": "38341.25",
      "Satış": "39308.9"
    },
    "14Ayaraltin": {
      "Alış": "3311.29",
      "Satış": "3314.51"
    },
    "18Ayaraltin": {
      "Alış": "4240.78",
      "Satış": "4244.9"
    },
    "22Ayarbilezik": {
      "Alış": "5298.06",
      "Satış": "5303.21"
    },
    "Ikibucukaltin": {
      "Alış": "92948.5",
      "Satış": "94434.4"
    },
    "Beslialtin": {
      "Alış": "188220.7",
      "Satış": "191892.56"
    },
    "Gremsealtin": {
      "Alış": "92948.5",
      "Satış": "95074.04"
    },
    "Resataltin": {
      "Alış": "38341.25",
      "Satış": "39308.9"
    },
    "Hamitaltin": {
      "Alış": "38341.25",
      "Satış": "39308.9"
    },
    "Gramplatin": {
      "Alış": "2292.57",
      "Satış": "2298.43"
    },
    "Grampaladyum": {
      "Alış": "2017.46",
      "Satış": "2025.9"
    }
  }
}