{
  "timestamp": "2025-08-29 12:52:02",
  "fiyatlar": {
    "Gramaltin": {
      "Alış": "4507.43",
      "Satış": "4507.87"
    },
    "Gumus": {
      "Alış": "51.36",
      "Satış": "51.4"
    },
    "Ons": {
      "Alış": "0",
      "Satış": "0"
    },
    "Gramhasaltin": {
      "Alış": "4484.87",
      "Satış": "4485.37"
    },
    "Ceyrekaltin": {
      "Alış": "7194.68",
      "Satış": "7357.23"
    },
    "Yarimaltin": {
      "Alış": "14344.39",
      "Satış": "14714.45"
    },
    "Tamaltin": {
      "Alış": "28778.71",
      "Satış": "29338.9"
    },
    "Cumhuriyetaltini": {
      "Alış": "29833",
      "Satış": "30284"
    },
    "Ataaltin": {
      "Alış": "29678.05",
      "Satış": "30418.86"
    },
    "14Ayaraltin": {
      "Alış": "2563.1",
      "Satış": "2564.9"
    },
    "18Ayaraltin": {
      "Alış": "3282.57",
      "Satış": "3284.88"
    },
    "22Ayarbilezik": {
      "Alış": "4100.97",
      "Satış": "4103.85"
    },
    "Ikibucukaltin": {
      "Alış": "71979.76",
      "Satış": "73110.74"
    },
    "Beslialtin": {
      "Alış": "145692.24",
      "Satış": "148494.46"
    },
    "Gremsealtin": {
      "Alış": "71946.78",
      "Satış": "73572.25"
    },
    "Resataltin": {
      "Alış": "29678.05",
      "Satış": "30418.86"
    },
    "Hamitaltin": {
      "Alış": "29678.05",
      "Satış": "30418.86"
    },
    "Gramplatin": {
      "Alış": "1783.01",
      "Satış": "1787.27"
    },
    "Grampaladyum": {
      "Alış": "1449.47",
      "Satış": "1455.17"
    }
  }
}