{
  "timestamp": "2026-04-17 12:44:03",
  "fiyatlar": {
    "Gramaltin": {
      "Alış": "6915.42",
      "Satış": "6916.24"
    },
    "Gumus": {
      "Alış": "114.93",
      "Satış": "115"
    },
    "Ons": {
      "Alış": "0",
      "Satış": "0"
    },
    "Gramhasaltin": {
      "Alış": "6880.84",
      "Satış": "6881.66"
    },
    "Ceyrekaltin": {
      "Alış": "11057.96",
      "Satış": "11309.74"
    },
    "Yarimaltin": {
      "Alış": "22046.82",
      "Satış": "22619.48"
    },
    "Tamaltin": {
      "Alış": "44231.86",
      "Satış": "45100.61"
    },
    "Cumhuriyetaltini": {
      "Alış": "45800",
      "Satış": "46494"
    },
    "Ataaltin": {
      "Alış": "45614.1",
      "Satış": "46760.76"
    },
    "14Ayaraltin": {
      "Alış": "3939.4",
      "Satış": "3942.85"
    },
    "18Ayaraltin": {
      "Alış": "5045.2",
      "Satış": "5049.61"
    },
    "22Ayarbilezik": {
      "Alış": "6303.04",
      "Satış": "6308.55"
    },
    "Ikibucukaltin": {
      "Alış": "110579.65",
      "Satış": "112336.5"
    },
    "Beslialtin": {
      "Alış": "223923.79",
      "Satış": "228269.98"
    },
    "Gremsealtin": {
      "Alış": "110579.65",
      "Satış": "113097.4"
    },
    "Resataltin": {
      "Alış": "45614.1",
      "Satış": "46760.76"
    },
    "Hamitaltin": {
      "Alış": "45614.1",
      "Satış": "46760.76"
    },
    "Gramplatin": {
      "Alış": "3020.54",
      "Satış": "3027.13"
    },
    "Grampaladyum": {
      "Alış": "2242.9",
      "Satış": "2249.93"
    }
  }
}