{
  "timestamp": "2025-09-16 16:55:02",
  "fiyatlar": {
    "Gramaltin": {
      "Alış": "4906.16",
      "Satış": "4906.67"
    },
    "Gumus": {
      "Alış": "56.98",
      "Satış": "57.03"
    },
    "Ons": {
      "Alış": "0",
      "Satış": "0"
    },
    "Gramhasaltin": {
      "Alış": "4881.62",
      "Satış": "4882.13"
    },
    "Ceyrekaltin": {
      "Alış": "8008.72",
      "Satış": "8191.26"
    },
    "Yarimaltin": {
      "Alış": "15967.38",
      "Satış": "16382.53"
    },
    "Tamaltin": {
      "Alış": "32034.86",
      "Satış": "32664.85"
    },
    "Cumhuriyetaltini": {
      "Alış": "33150",
      "Satış": "33651"
    },
    "Ataaltin": {
      "Alış": "33035.95",
      "Satış": "33867.24"
    },
    "14Ayaraltin": {
      "Alış": "2853.1",
      "Satış": "2855.67"
    },
    "18Ayaraltin": {
      "Alış": "3653.98",
      "Satış": "3657.26"
    },
    "22Ayarbilezik": {
      "Alış": "4564.97",
      "Satış": "4569.07"
    },
    "Ikibucukaltin": {
      "Alış": "80087.15",
      "Satış": "81361.54"
    },
    "Beslialtin": {
      "Alış": "162176.48",
      "Satış": "165328.25"
    },
    "Gremsealtin": {
      "Alış": "80087.15",
      "Satış": "81912.63"
    },
    "Resataltin": {
      "Alış": "33035.95",
      "Satış": "33867.24"
    },
    "Hamitaltin": {
      "Alış": "33035.95",
      "Satış": "33867.24"
    },
    "Gramplatin": {
      "Alış": "1846.49",
      "Satış": "1849.64"
    },
    "Grampaladyum": {
      "Alış": "1566.02",
      "Satış": "1572.1"
    }
  }
}